setup.py
MemeDensity/__init__.py
MemeDensity/command_line.py
memedensity.egg-info/PKG-INFO
memedensity.egg-info/SOURCES.txt
memedensity.egg-info/dependency_links.txt
memedensity.egg-info/entry_points.txt
memedensity.egg-info/requires.txt
memedensity.egg-info/top_level.txt