Metadata-Version: 1.0
Name: memedensity
Version: 0.0.2
Summary: Tells you the amount of memes in your facebook feed
Home-page: https://github.com/lakshaykalbhor/MemeDensity
Author: Lakshay Kalbhor
Author-email: lakshaykalbhor@gmail.com
License: MIT
Platform: UNKNOWN
